febid/start.py
febid/diffusion.py
febid/continuum_model_base.py
febid/Process.py
febid/mlcca.py
febid/kernel_modules.py
febid/simple_patterns.py
febid/__init__.py
febid/slice_trics.py
febid/__main__.py
febid/febid_core.py
febid/Statistics.py
febid/expressions.py
febid/parameter_scanning.py
febid/Structure.py
febid/heat_transfer.py
febid/libraries/pde/tridiag.c
febid/libraries/pde/tridiag.cpython-39-x86_64-linux-gnu.so
febid/libraries/pde/__init__.py
febid/libraries/pde/tridiag.pyx
febid/libraries/ray_traversal/traversal.pyx
febid/libraries/ray_traversal/traversal.c
febid/libraries/ray_traversal/__init__.py
febid/libraries/ray_traversal/traversal.cpython-39-x86_64-linux-gnu.so
febid/libraries/vtk_rendering/show_animation_new.py
febid/libraries/vtk_rendering/__init__.py
febid/libraries/vtk_rendering/VTK_Rendering.py
febid/libraries/vtk_rendering/show_file.py
febid/libraries/rolling/roll.c
febid/libraries/rolling/roll.pyx
febid/libraries/rolling/roll.cpython-39-x86_64-linux-gnu.so
febid/libraries/rolling/__init__.py
febid/monte_carlo/mc_base.py
febid/monte_carlo/etraj3d.py
febid/monte_carlo/etrajmap3d.py
febid/monte_carlo/etrajectory.py
febid/monte_carlo/__init__.py
febid/monte_carlo/compiled/etrajectory_c.cpp
febid/monte_carlo/compiled/setup.py
febid/monte_carlo/compiled/etrajectory_c.pyx
febid/monte_carlo/compiled/etrajectory_c.cpython-39-x86_64-linux-gnu.so
febid/ui/last_session_stub.yml
febid/ui/process_viz.py
febid/ui/main_window.py
febid/ui/__init__.py
febid/ui/ui_shell.py
febid/kernels/up_surface.cl
febid/kernels/ret_slice_bool.cl
febid/kernels/return_slice.cl
febid/kernels/dep_prec_den.cl
febid-0.10.0.dist-info/WHEEL
febid-0.10.0.dist-info/top_level.txt
febid-0.10.0.dist-info/RECORD
febid-0.10.0.dist-info/METADATA
febid-0.10.0.dist-info/licenses/LICENSE
