Metadata-Version: 2.4
Name: febid
Version: 0.10.0
Summary: FEBID process simulator
Home-page: https://github.com/MrCheatak/FEBID_py
Author: Alexander Kuprava, Michael Huth
Author-email: sandro1742@gmail.com
License: APGL-3.0
License-File: LICENSE
Requires-Dist: numpy==1.26.4
Requires-Dist: pyvista==0.44.2
Requires-Dist: pyvistaqt==0.11.1
Requires-Dist: pandas==2.2.2
Requires-Dist: ruamel.yaml==0.18.6
Requires-Dist: pyyaml==6.0.2
Requires-Dist: cython
Requires-Dist: openpyxl==3.1.2
Requires-Dist: tqdm
Requires-Dist: pyqt5
Requires-Dist: vtk
Requires-Dist: numexpr_mod
Requires-Dist: loky~=3.4.1
Requires-Dist: pyopencl
Dynamic: author
Dynamic: author-email
Dynamic: description
Dynamic: description-content-type
Dynamic: home-page
Dynamic: license
Dynamic: license-file
Dynamic: requires-dist
Dynamic: summary
